ogame_stats/__init__.py
ogame_stats/highscores_api.py
ogame_stats/universe_api.py
ogame_stats/universes_api.py
ogame_stats/utils.py
ogame_stats-0.3.6.dist-info/LICENSE
ogame_stats-0.3.6.dist-info/METADATA
ogame_stats-0.3.6.dist-info/WHEEL
ogame_stats-0.3.6.dist-info/top_level.txt
ogame_stats-0.3.6.dist-info/RECORD
