Metadata-Version: 2.1
Name: ogame-stats
Version: 0.3.6
Summary: wrapper around public game statistics for https://ogame.org
Home-page: https://github.com/erkandem/ogame-stats
Author: Erkan Demiralay
Author-email: erkan.dem@pm.me
License: UNKNOWN
Project-URL: Bug Reports, https://github.com/erkandem/ogame-stats/issues
Project-URL: Source, https://github.com/erkandem/ogame-stats/
Keywords: ogame
Platform: UNKNOWN
Classifier: Development Status :: 3 - Alpha
Classifier: Intended Audience :: Developers
Classifier: Topic :: Games/Entertainment :: Simulation
Classifier: License :: OSI Approved :: MIT License
Classifier: Programming Language :: Python :: 3
Classifier: Programming Language :: Python :: 3.6
Classifier: Programming Language :: Python :: 3.7
Classifier: Programming Language :: Python :: 3.8
Requires-Python: >=3.6, <4
Requires-Dist: pandas
Requires-Dist: requests
Requires-Dist: xmltodict
Provides-Extra: dev
Requires-Dist: coverage ; extra == 'dev'
Requires-Dist: pytest ; extra == 'dev'
Requires-Dist: wheel ; extra == 'dev'
